{
  "home": "Thuise",
  "events": "Evenementen",
  "contactUs": "Neem contact op",
  "language": "Taal",
  "navigation": "Navigatie",
  "searchForEvent": "Evenement zoeken...",
  "nextUp": "Volgende",
  "upComing": "AANSTAAND",
  "check": "Controleren",
  "save": "Sparen",
  "buy": "Koop nu",
  "seeAll": "Alles zien",
  "bilets&Info": "Bilets & Info",
  "getInTouch": "Neem contact op",
  "submit": "Indienen",
  "ourOffice": "Ons kantoor",
  "name": "Naam",
  "email": "Email",
  "yourMessage": "Jouw Bericht...",
  "contactInfo": "Contact Informatie",
  "followUs": "Volg ons!"
}
